[
    {
        "year": 2013, 
        "id": "bali", 
        "imageUrl": "img/Amed.jpg", 
        "name": "Bali Tour",
		"description": "All around Bali during 3 weeks"
	}, 
    {
        "year": 2012, 
        "id": "sardinia", 
        "imageUrl": "img/Piscinas.jpg", 
        "name": "Sea and sun in Sardinia",
		"description": "Quietness in Sardinia's wonderful nature"
    }, 
    {
        "year": 2012, 
        "id": "china", 
        "imageUrl": "img/Temple of Heaven.jpg", 
        "name": "Discover China",
		"description": "A great discovery of the Chinese civilization"
    }, 
    {
        "year": 2011, 
        "id": "tanzania", 
        "imageUrl": "img/Tanzania.jpg", 
        "name": "The wilderness of Tanzania",
		"description": "Such a wonderful travel"
    }
]
